main/AutoitExecutor.py
main/GAutoit.py
main/GUIA.py
main/OperationSet.py
main/__init__.py
main/autoitX.py
main/decorator.py
main/demo.py
main/error.py
main/test.py
main/uia_extend.py
main/加密.py
executor1-1.0.0.dist-info/METADATA
executor1-1.0.0.dist-info/WHEEL
executor1-1.0.0.dist-info/top_level.txt
executor1-1.0.0.dist-info/RECORD
