Metadata-Version: 2.1
Name: executor1
Version: 1.0.0
Summary: The configuration file is automatically executed
Home-page: http://gitlab.bczx365.com/rpa/UIA_Executor
Author: rejii
Author-email: ljy@bczx365.com
License: MIT
Keywords: uiautomation,autoit,python
Platform: UNKNOWN
Requires-Python: >=3.6.0
Requires-Dist: pyautoit
Requires-Dist: uiautomation
